seres.py
seres-0.0.1.dist-info/METADATA
seres-0.0.1.dist-info/WHEEL
seres-0.0.1.dist-info/entry_points.txt
seres-0.0.1.dist-info/top_level.txt
seres-0.0.1.dist-info/RECORD
