Metadata-Version: 2.1
Name: seres
Version: 0.0.1
Requires-Dist: click
